{
  "embed": "<iframe src=\"https://www.pornhub.com/embed/009af4d34db106d3e2a7\" frameborder=\"0\" height=\"481\" width=\"608\" scrolling=\"no\"></iframe>",
  "thumbnail": "https://ei.phncdn.com/videos/201011/01/95558/original/(m=eaf8GgaaaWavb)(mh=CiQraKtVprv6Op-a)7.jpg",
  "screenshots": [
    "https://ei.phncdn.com/videos/201011/01/95558/original/(m=eaf8GgaaaWavb)(mh=CiQraKtVprv6Op-a)1.jpg",
    "https://ei.phncdn.com/videos/201011/01/95558/original/(m=eaf8GgaaaWavb)(mh=CiQraKtVprv6Op-a)2.jpg",
    "https://ei.phncdn.com/videos/201011/01/95558/original/(m=eaf8GgaaaWavb)(mh=CiQraKtVprv6Op-a)3.jpg",
    "https://ei.phncdn.com/videos/201011/01/95558/original/(m=eaf8GgaaaWavb)(mh=CiQraKtVprv6Op-a)4.jpg",
    "https://ei.phncdn.com/videos/201011/01/95558/original/(m=eaf8GgaaaWavb)(mh=CiQraKtVprv6Op-a)5.jpg",
    "https://ei.phncdn.com/videos/201011/01/95558/original/(m=eaf8GgaaaWavb)(mh=CiQraKtVprv6Op-a)6.jpg",
    "https://ei.phncdn.com/videos/201011/01/95558/original/(m=eaf8GgaaaWavb)(mh=CiQraKtVprv6Op-a)7.jpg",
    "https://ei.phncdn.com/videos/201011/01/95558/original/(m=eaf8GgaaaWavb)(mh=CiQraKtVprv6Op-a)8.jpg",
    "https://ei.phncdn.com/videos/201011/01/95558/original/(m=eaf8GgaaaWavb)(mh=CiQraKtVprv6Op-a)9.jpg",
    "https://ei.phncdn.com/videos/201011/01/95558/original/(m=eaf8GgaaaWavb)(mh=CiQraKtVprv6Op-a)10.jpg",
    "https://ei.phncdn.com/videos/201011/01/95558/original/(m=eaf8GgaaaWavb)(mh=CiQraKtVprv6Op-a)11.jpg",
    "https://ei.phncdn.com/videos/201011/01/95558/original/(m=eaf8GgaaaWavb)(mh=CiQraKtVprv6Op-a)12.jpg",
    "https://ei.phncdn.com/videos/201011/01/95558/original/(m=eaf8GgaaaWavb)(mh=CiQraKtVprv6Op-a)13.jpg",
    "https://ei.phncdn.com/videos/201011/01/95558/original/(m=eaf8GgaaaWavb)(mh=CiQraKtVprv6Op-a)14.jpg",
    "https://ei.phncdn.com/videos/201011/01/95558/original/(m=eaf8GgaaaWavb)(mh=CiQraKtVprv6Op-a)15.jpg",
    "https://ei.phncdn.com/videos/201011/01/95558/original/(m=eaf8GgaaaWavb)(mh=CiQraKtVprv6Op-a)16.jpg"
  ],
  "title": "Jazzmine - The Pool Party - Scene 4",
  "tags": [
    "pool",
    "big-tits",
    "asian",
    "blonde",
    "outdoor",
    "blowjob",
    "hardcore",
    "party",
    "hunk",
    "muscle",
    "tattoo"
  ],
  "categories": [
    "Asian",
    "Big Tits",
    "Pornstar",
    "Party"
  ],
  "performers": [
    "Adam Wilde",
    "Jazzmine"
  ],
  "duration": 1145,
  "views": 695724,
  "likes": 559,
  "dislikes": 101
}