{
  "embed": "<iframe src=\"https://www.pornhub.com/embed/792551388\" frameborder=\"0\" height=\"481\" width=\"608\" scrolling=\"no\"></iframe>",
  "thumbnail": "https://ei.phncdn.com/videos/201004/22/1054884/original/(m=eaf8GgaaaWavb)(mh=vayO-iDmq5iXJyQV)8.jpg",
  "screenshots": [
    "https://ei.phncdn.com/videos/201004/22/1054884/original/(m=eaf8GgaaaWavb)(mh=vayO-iDmq5iXJyQV)1.jpg",
    "https://ei.phncdn.com/videos/201004/22/1054884/original/(m=eaf8GgaaaWavb)(mh=vayO-iDmq5iXJyQV)2.jpg",
    "https://ei.phncdn.com/videos/201004/22/1054884/original/(m=eaf8GgaaaWavb)(mh=vayO-iDmq5iXJyQV)3.jpg",
    "https://ei.phncdn.com/videos/201004/22/1054884/original/(m=eaf8GgaaaWavb)(mh=vayO-iDmq5iXJyQV)4.jpg",
    "https://ei.phncdn.com/videos/201004/22/1054884/original/(m=eaf8GgaaaWavb)(mh=vayO-iDmq5iXJyQV)5.jpg",
    "https://ei.phncdn.com/videos/201004/22/1054884/original/(m=eaf8GgaaaWavb)(mh=vayO-iDmq5iXJyQV)6.jpg",
    "https://ei.phncdn.com/videos/201004/22/1054884/original/(m=eaf8GgaaaWavb)(mh=vayO-iDmq5iXJyQV)7.jpg",
    "https://ei.phncdn.com/videos/201004/22/1054884/original/(m=eaf8GgaaaWavb)(mh=vayO-iDmq5iXJyQV)8.jpg",
    "https://ei.phncdn.com/videos/201004/22/1054884/original/(m=eaf8GgaaaWavb)(mh=vayO-iDmq5iXJyQV)9.jpg",
    "https://ei.phncdn.com/videos/201004/22/1054884/original/(m=eaf8GgaaaWavb)(mh=vayO-iDmq5iXJyQV)10.jpg",
    "https://ei.phncdn.com/videos/201004/22/1054884/original/(m=eaf8GgaaaWavb)(mh=vayO-iDmq5iXJyQV)11.jpg",
    "https://ei.phncdn.com/videos/201004/22/1054884/original/(m=eaf8GgaaaWavb)(mh=vayO-iDmq5iXJyQV)12.jpg",
    "https://ei.phncdn.com/videos/201004/22/1054884/original/(m=eaf8GgaaaWavb)(mh=vayO-iDmq5iXJyQV)13.jpg",
    "https://ei.phncdn.com/videos/201004/22/1054884/original/(m=eaf8GgaaaWavb)(mh=vayO-iDmq5iXJyQV)14.jpg",
    "https://ei.phncdn.com/videos/201004/22/1054884/original/(m=eaf8GgaaaWavb)(mh=vayO-iDmq5iXJyQV)15.jpg",
    "https://ei.phncdn.com/videos/201004/22/1054884/original/(m=eaf8GgaaaWavb)(mh=vayO-iDmq5iXJyQV)16.jpg"
  ],
  "title": "Strap-on Defloration",
  "tags": [
    "sclip",
    "strap-on",
    "dildo",
    "german",
    "fuck",
    "lesbian",
    "outdoor",
    "beach",
    "pussylicking",
    "toys",
    "amateur",
    "homemade"
  ],
  "categories": [
    "Amateur",
    "Toys",
    "Public",
    "Lesbian"
  ],
  "performers": [
    ""
  ],
  "duration": 554,
  "views": 1158977,
  "likes": 1032,
  "dislikes": 357
}