{
  "embed": "<iframe src=\"https://www.pornhub.com/embed/32d3496eddfd0bb88a45\" frameborder=\"0\" height=\"481\" width=\"608\" scrolling=\"no\"></iframe>",
  "thumbnail": "https://ei.phncdn.com/videos/201011/01/95618/original/(m=eaf8GgaaaWavb)(mh=v1MYsZvkdyfA5h_v)7.jpg",
  "screenshots": [
    "https://ei.phncdn.com/videos/201011/01/95618/original/(m=eaf8GgaaaWavb)(mh=v1MYsZvkdyfA5h_v)1.jpg",
    "https://ei.phncdn.com/videos/201011/01/95618/original/(m=eaf8GgaaaWavb)(mh=v1MYsZvkdyfA5h_v)2.jpg",
    "https://ei.phncdn.com/videos/201011/01/95618/original/(m=eaf8GgaaaWavb)(mh=v1MYsZvkdyfA5h_v)3.jpg",
    "https://ei.phncdn.com/videos/201011/01/95618/original/(m=eaf8GgaaaWavb)(mh=v1MYsZvkdyfA5h_v)4.jpg",
    "https://ei.phncdn.com/videos/201011/01/95618/original/(m=eaf8GgaaaWavb)(mh=v1MYsZvkdyfA5h_v)5.jpg",
    "https://ei.phncdn.com/videos/201011/01/95618/original/(m=eaf8GgaaaWavb)(mh=v1MYsZvkdyfA5h_v)6.jpg",
    "https://ei.phncdn.com/videos/201011/01/95618/original/(m=eaf8GgaaaWavb)(mh=v1MYsZvkdyfA5h_v)7.jpg",
    "https://ei.phncdn.com/videos/201011/01/95618/original/(m=eaf8GgaaaWavb)(mh=v1MYsZvkdyfA5h_v)8.jpg",
    "https://ei.phncdn.com/videos/201011/01/95618/original/(m=eaf8GgaaaWavb)(mh=v1MYsZvkdyfA5h_v)9.jpg",
    "https://ei.phncdn.com/videos/201011/01/95618/original/(m=eaf8GgaaaWavb)(mh=v1MYsZvkdyfA5h_v)10.jpg",
    "https://ei.phncdn.com/videos/201011/01/95618/original/(m=eaf8GgaaaWavb)(mh=v1MYsZvkdyfA5h_v)11.jpg",
    "https://ei.phncdn.com/videos/201011/01/95618/original/(m=eaf8GgaaaWavb)(mh=v1MYsZvkdyfA5h_v)12.jpg",
    "https://ei.phncdn.com/videos/201011/01/95618/original/(m=eaf8GgaaaWavb)(mh=v1MYsZvkdyfA5h_v)13.jpg",
    "https://ei.phncdn.com/videos/201011/01/95618/original/(m=eaf8GgaaaWavb)(mh=v1MYsZvkdyfA5h_v)14.jpg",
    "https://ei.phncdn.com/videos/201011/01/95618/original/(m=eaf8GgaaaWavb)(mh=v1MYsZvkdyfA5h_v)15.jpg",
    "https://ei.phncdn.com/videos/201011/01/95618/original/(m=eaf8GgaaaWavb)(mh=v1MYsZvkdyfA5h_v)16.jpg"
  ],
  "title": "Chrissy Tyler - Lick It, Suck It & Fuck It - Scene 4",
  "tags": [
    "pornstar",
    "ass",
    "teen",
    "tight-ass",
    "licking",
    "blowjob",
    "anal",
    "pussy",
    "riding",
    "fingering",
    "big-tits",
    "natural-tits"
  ],
  "categories": [
    "Hardcore",
    "Pornstar",
    "18-25"
  ],
  "performers": [
    "Chrissy Taylor",
    "chrissy tyler"
  ],
  "duration": 954,
  "views": 174734,
  "likes": 143,
  "dislikes": 32
}