{
  "embed": "<iframe src=\"https://www.pornhub.com/embed/44edd542583327129b9e\" frameborder=\"0\" height=\"481\" width=\"608\" scrolling=\"no\"></iframe>",
  "thumbnail": "https://ei.phncdn.com/videos/201011/01/104085/original/(m=eaf8GgaaaWavb)(mh=uJCYSC_eD8090rOJ)12.jpg",
  "screenshots": [
    "https://ei.phncdn.com/videos/201011/01/104085/original/(m=eaf8GgaaaWavb)(mh=uJCYSC_eD8090rOJ)1.jpg",
    "https://ei.phncdn.com/videos/201011/01/104085/original/(m=eaf8GgaaaWavb)(mh=uJCYSC_eD8090rOJ)2.jpg",
    "https://ei.phncdn.com/videos/201011/01/104085/original/(m=eaf8GgaaaWavb)(mh=uJCYSC_eD8090rOJ)3.jpg",
    "https://ei.phncdn.com/videos/201011/01/104085/original/(m=eaf8GgaaaWavb)(mh=uJCYSC_eD8090rOJ)4.jpg",
    "https://ei.phncdn.com/videos/201011/01/104085/original/(m=eaf8GgaaaWavb)(mh=uJCYSC_eD8090rOJ)5.jpg",
    "https://ei.phncdn.com/videos/201011/01/104085/original/(m=eaf8GgaaaWavb)(mh=uJCYSC_eD8090rOJ)6.jpg",
    "https://ei.phncdn.com/videos/201011/01/104085/original/(m=eaf8GgaaaWavb)(mh=uJCYSC_eD8090rOJ)7.jpg",
    "https://ei.phncdn.com/videos/201011/01/104085/original/(m=eaf8GgaaaWavb)(mh=uJCYSC_eD8090rOJ)8.jpg",
    "https://ei.phncdn.com/videos/201011/01/104085/original/(m=eaf8GgaaaWavb)(mh=uJCYSC_eD8090rOJ)9.jpg",
    "https://ei.phncdn.com/videos/201011/01/104085/original/(m=eaf8GgaaaWavb)(mh=uJCYSC_eD8090rOJ)10.jpg",
    "https://ei.phncdn.com/videos/201011/01/104085/original/(m=eaf8GgaaaWavb)(mh=uJCYSC_eD8090rOJ)11.jpg",
    "https://ei.phncdn.com/videos/201011/01/104085/original/(m=eaf8GgaaaWavb)(mh=uJCYSC_eD8090rOJ)12.jpg",
    "https://ei.phncdn.com/videos/201011/01/104085/original/(m=eaf8GgaaaWavb)(mh=uJCYSC_eD8090rOJ)13.jpg",
    "https://ei.phncdn.com/videos/201011/01/104085/original/(m=eaf8GgaaaWavb)(mh=uJCYSC_eD8090rOJ)14.jpg",
    "https://ei.phncdn.com/videos/201011/01/104085/original/(m=eaf8GgaaaWavb)(mh=uJCYSC_eD8090rOJ)15.jpg",
    "https://ei.phncdn.com/videos/201011/01/104085/original/(m=eaf8GgaaaWavb)(mh=uJCYSC_eD8090rOJ)16.jpg"
  ],
  "title": "Kameron Styles - Baby Doll Bodyguards - Scene 2",
  "tags": [
    "pornstar",
    "tight",
    "teen",
    "teasing",
    "pussy",
    "rubbing",
    "blowjob",
    "deepthroat",
    "doggystyle",
    "hardcore",
    "pussylicking",
    "cumshot",
    "reality",
    "brunette",
    "facial"
  ],
  "categories": [
    "Brunette",
    "Pornstar",
    "Reality",
    "18-25"
  ],
  "performers": [
    "baby doll",
    "Cameron Styles"
  ],
  "duration": 938,
  "views": 369603,
  "likes": 503,
  "dislikes": 76
}