{
  "embed": "<iframe src=\"https://www.pornhub.com/embed/bfb9ee4c3e504c4b5b5f\" frameborder=\"0\" height=\"481\" width=\"608\" scrolling=\"no\"></iframe>",
  "thumbnail": "https://ei.phncdn.com/videos/201011/01/97352/original/(m=eaf8GgaaaWavb)(mh=TW7qrvtLMJhNuz5U)13.jpg",
  "screenshots": [
    "https://ei.phncdn.com/videos/201011/01/97352/original/(m=eaf8GgaaaWavb)(mh=TW7qrvtLMJhNuz5U)1.jpg",
    "https://ei.phncdn.com/videos/201011/01/97352/original/(m=eaf8GgaaaWavb)(mh=TW7qrvtLMJhNuz5U)2.jpg",
    "https://ei.phncdn.com/videos/201011/01/97352/original/(m=eaf8GgaaaWavb)(mh=TW7qrvtLMJhNuz5U)3.jpg",
    "https://ei.phncdn.com/videos/201011/01/97352/original/(m=eaf8GgaaaWavb)(mh=TW7qrvtLMJhNuz5U)4.jpg",
    "https://ei.phncdn.com/videos/201011/01/97352/original/(m=eaf8GgaaaWavb)(mh=TW7qrvtLMJhNuz5U)5.jpg",
    "https://ei.phncdn.com/videos/201011/01/97352/original/(m=eaf8GgaaaWavb)(mh=TW7qrvtLMJhNuz5U)6.jpg",
    "https://ei.phncdn.com/videos/201011/01/97352/original/(m=eaf8GgaaaWavb)(mh=TW7qrvtLMJhNuz5U)7.jpg",
    "https://ei.phncdn.com/videos/201011/01/97352/original/(m=eaf8GgaaaWavb)(mh=TW7qrvtLMJhNuz5U)8.jpg",
    "https://ei.phncdn.com/videos/201011/01/97352/original/(m=eaf8GgaaaWavb)(mh=TW7qrvtLMJhNuz5U)9.jpg",
    "https://ei.phncdn.com/videos/201011/01/97352/original/(m=eaf8GgaaaWavb)(mh=TW7qrvtLMJhNuz5U)10.jpg",
    "https://ei.phncdn.com/videos/201011/01/97352/original/(m=eaf8GgaaaWavb)(mh=TW7qrvtLMJhNuz5U)11.jpg",
    "https://ei.phncdn.com/videos/201011/01/97352/original/(m=eaf8GgaaaWavb)(mh=TW7qrvtLMJhNuz5U)12.jpg",
    "https://ei.phncdn.com/videos/201011/01/97352/original/(m=eaf8GgaaaWavb)(mh=TW7qrvtLMJhNuz5U)13.jpg",
    "https://ei.phncdn.com/videos/201011/01/97352/original/(m=eaf8GgaaaWavb)(mh=TW7qrvtLMJhNuz5U)14.jpg",
    "https://ei.phncdn.com/videos/201011/01/97352/original/(m=eaf8GgaaaWavb)(mh=TW7qrvtLMJhNuz5U)15.jpg",
    "https://ei.phncdn.com/videos/201011/01/97352/original/(m=eaf8GgaaaWavb)(mh=TW7qrvtLMJhNuz5U)16.jpg"
  ],
  "title": "Austin Kincaid - Rock Hard #4 - Scene 4",
  "tags": [
    "austin",
    "kindaid",
    "rock",
    "hard",
    "pornstar",
    "brunette",
    "bigtits",
    "facial",
    "babe",
    "doggystyle",
    "blowjob",
    "native",
    "big-dick",
    "cherokee"
  ],
  "categories": [
    "Brunette",
    "Pornstar"
  ],
  "performers": [
    "Austin Kincaid",
    "Ben English"
  ],
  "duration": 1590,
  "views": 2841737,
  "likes": 3715,
  "dislikes": 656
}