{
  "embed": "<iframe src=\"https://www.pornhub.com/embed/5cdc68ed249c9f6ad504\" frameborder=\"0\" height=\"481\" width=\"608\" scrolling=\"no\"></iframe>",
  "thumbnail": "https://ei.phncdn.com/videos/201011/01/95067/original/(m=eaf8GgaaaWavb)(mh=AfXAOx4_zIjPrAfM)15.jpg",
  "screenshots": [
    "https://ei.phncdn.com/videos/201011/01/95067/original/(m=eaf8GgaaaWavb)(mh=AfXAOx4_zIjPrAfM)1.jpg",
    "https://ei.phncdn.com/videos/201011/01/95067/original/(m=eaf8GgaaaWavb)(mh=AfXAOx4_zIjPrAfM)2.jpg",
    "https://ei.phncdn.com/videos/201011/01/95067/original/(m=eaf8GgaaaWavb)(mh=AfXAOx4_zIjPrAfM)3.jpg",
    "https://ei.phncdn.com/videos/201011/01/95067/original/(m=eaf8GgaaaWavb)(mh=AfXAOx4_zIjPrAfM)4.jpg",
    "https://ei.phncdn.com/videos/201011/01/95067/original/(m=eaf8GgaaaWavb)(mh=AfXAOx4_zIjPrAfM)5.jpg",
    "https://ei.phncdn.com/videos/201011/01/95067/original/(m=eaf8GgaaaWavb)(mh=AfXAOx4_zIjPrAfM)6.jpg",
    "https://ei.phncdn.com/videos/201011/01/95067/original/(m=eaf8GgaaaWavb)(mh=AfXAOx4_zIjPrAfM)7.jpg",
    "https://ei.phncdn.com/videos/201011/01/95067/original/(m=eaf8GgaaaWavb)(mh=AfXAOx4_zIjPrAfM)8.jpg",
    "https://ei.phncdn.com/videos/201011/01/95067/original/(m=eaf8GgaaaWavb)(mh=AfXAOx4_zIjPrAfM)9.jpg",
    "https://ei.phncdn.com/videos/201011/01/95067/original/(m=eaf8GgaaaWavb)(mh=AfXAOx4_zIjPrAfM)10.jpg",
    "https://ei.phncdn.com/videos/201011/01/95067/original/(m=eaf8GgaaaWavb)(mh=AfXAOx4_zIjPrAfM)11.jpg",
    "https://ei.phncdn.com/videos/201011/01/95067/original/(m=eaf8GgaaaWavb)(mh=AfXAOx4_zIjPrAfM)12.jpg",
    "https://ei.phncdn.com/videos/201011/01/95067/original/(m=eaf8GgaaaWavb)(mh=AfXAOx4_zIjPrAfM)13.jpg",
    "https://ei.phncdn.com/videos/201011/01/95067/original/(m=eaf8GgaaaWavb)(mh=AfXAOx4_zIjPrAfM)14.jpg",
    "https://ei.phncdn.com/videos/201011/01/95067/original/(m=eaf8GgaaaWavb)(mh=AfXAOx4_zIjPrAfM)15.jpg",
    "https://ei.phncdn.com/videos/201011/01/95067/original/(m=eaf8GgaaaWavb)(mh=AfXAOx4_zIjPrAfM)16.jpg"
  ],
  "title": "Alexis Malone & Teanna Kai - Pool Shark - Scene 6",
  "tags": [
    "lesbian",
    "brunette",
    "asian",
    "big-tits",
    "strap-on",
    "toys",
    "reality",
    "babe",
    "rubbing",
    "pussy",
    "pussylicking",
    "fingering",
    "pornstar",
    "blonde",
    "fake-tits",
    "natural-tits"
  ],
  "categories": [
    "Asian",
    "Lesbian",
    "Pornstar"
  ],
  "performers": [
    "Alexis Malone",
    "Teanna Kai"
  ],
  "duration": 892,
  "views": 1387417,
  "likes": 1853,
  "dislikes": 280
}