{
  "embed": "<iframe src=\"https://www.pornhub.com/embed/9b02936abe7bddbc0a09\" frameborder=\"0\" height=\"481\" width=\"608\" scrolling=\"no\"></iframe>",
  "thumbnail": "https://ei.phncdn.com/videos/201011/01/103194/original/(m=eaf8GgaaaWavb)(mh=dMyUVhHnmuNOmtA9)14.jpg",
  "screenshots": [
    "https://ei.phncdn.com/videos/201011/01/103194/original/(m=eaf8GgaaaWavb)(mh=dMyUVhHnmuNOmtA9)1.jpg",
    "https://ei.phncdn.com/videos/201011/01/103194/original/(m=eaf8GgaaaWavb)(mh=dMyUVhHnmuNOmtA9)2.jpg",
    "https://ei.phncdn.com/videos/201011/01/103194/original/(m=eaf8GgaaaWavb)(mh=dMyUVhHnmuNOmtA9)3.jpg",
    "https://ei.phncdn.com/videos/201011/01/103194/original/(m=eaf8GgaaaWavb)(mh=dMyUVhHnmuNOmtA9)4.jpg",
    "https://ei.phncdn.com/videos/201011/01/103194/original/(m=eaf8GgaaaWavb)(mh=dMyUVhHnmuNOmtA9)5.jpg",
    "https://ei.phncdn.com/videos/201011/01/103194/original/(m=eaf8GgaaaWavb)(mh=dMyUVhHnmuNOmtA9)6.jpg",
    "https://ei.phncdn.com/videos/201011/01/103194/original/(m=eaf8GgaaaWavb)(mh=dMyUVhHnmuNOmtA9)7.jpg",
    "https://ei.phncdn.com/videos/201011/01/103194/original/(m=eaf8GgaaaWavb)(mh=dMyUVhHnmuNOmtA9)8.jpg",
    "https://ei.phncdn.com/videos/201011/01/103194/original/(m=eaf8GgaaaWavb)(mh=dMyUVhHnmuNOmtA9)9.jpg",
    "https://ei.phncdn.com/videos/201011/01/103194/original/(m=eaf8GgaaaWavb)(mh=dMyUVhHnmuNOmtA9)10.jpg",
    "https://ei.phncdn.com/videos/201011/01/103194/original/(m=eaf8GgaaaWavb)(mh=dMyUVhHnmuNOmtA9)11.jpg",
    "https://ei.phncdn.com/videos/201011/01/103194/original/(m=eaf8GgaaaWavb)(mh=dMyUVhHnmuNOmtA9)12.jpg",
    "https://ei.phncdn.com/videos/201011/01/103194/original/(m=eaf8GgaaaWavb)(mh=dMyUVhHnmuNOmtA9)13.jpg",
    "https://ei.phncdn.com/videos/201011/01/103194/original/(m=eaf8GgaaaWavb)(mh=dMyUVhHnmuNOmtA9)14.jpg",
    "https://ei.phncdn.com/videos/201011/01/103194/original/(m=eaf8GgaaaWavb)(mh=dMyUVhHnmuNOmtA9)15.jpg",
    "https://ei.phncdn.com/videos/201011/01/103194/original/(m=eaf8GgaaaWavb)(mh=dMyUVhHnmuNOmtA9)16.jpg"
  ],
  "title": "Aveena Lee - Pretty Peaches - Scene 6",
  "tags": [
    "reality",
    "asian",
    "pornstar",
    "tight",
    "teasing",
    "blowjob",
    "pussy",
    "rubbing",
    "riding",
    "pussylicking",
    "hardcore",
    "doggystyle",
    "spanking",
    "cumshot",
    "raven"
  ],
  "categories": [
    "Asian",
    "Hardcore",
    "Pornstar"
  ],
  "performers": [
    "Avena Lee"
  ],
  "duration": 963,
  "views": 431948,
  "likes": 553,
  "dislikes": 89
}