{
  "embed": "<iframe src=\"https://www.pornhub.com/embed/408326769\" frameborder=\"0\" height=\"481\" width=\"608\" scrolling=\"no\"></iframe>",
  "thumbnail": "https://ei.phncdn.com/videos/201004/21/1054308/original/(m=eaf8GgaaaWavb)(mh=kDmJsnjRCp84_VhO)12.jpg",
  "screenshots": [
    "https://ei.phncdn.com/videos/201004/21/1054308/original/(m=eaf8GgaaaWavb)(mh=kDmJsnjRCp84_VhO)1.jpg",
    "https://ei.phncdn.com/videos/201004/21/1054308/original/(m=eaf8GgaaaWavb)(mh=kDmJsnjRCp84_VhO)2.jpg",
    "https://ei.phncdn.com/videos/201004/21/1054308/original/(m=eaf8GgaaaWavb)(mh=kDmJsnjRCp84_VhO)3.jpg",
    "https://ei.phncdn.com/videos/201004/21/1054308/original/(m=eaf8GgaaaWavb)(mh=kDmJsnjRCp84_VhO)4.jpg",
    "https://ei.phncdn.com/videos/201004/21/1054308/original/(m=eaf8GgaaaWavb)(mh=kDmJsnjRCp84_VhO)5.jpg",
    "https://ei.phncdn.com/videos/201004/21/1054308/original/(m=eaf8GgaaaWavb)(mh=kDmJsnjRCp84_VhO)6.jpg",
    "https://ei.phncdn.com/videos/201004/21/1054308/original/(m=eaf8GgaaaWavb)(mh=kDmJsnjRCp84_VhO)7.jpg",
    "https://ei.phncdn.com/videos/201004/21/1054308/original/(m=eaf8GgaaaWavb)(mh=kDmJsnjRCp84_VhO)8.jpg",
    "https://ei.phncdn.com/videos/201004/21/1054308/original/(m=eaf8GgaaaWavb)(mh=kDmJsnjRCp84_VhO)9.jpg",
    "https://ei.phncdn.com/videos/201004/21/1054308/original/(m=eaf8GgaaaWavb)(mh=kDmJsnjRCp84_VhO)10.jpg",
    "https://ei.phncdn.com/videos/201004/21/1054308/original/(m=eaf8GgaaaWavb)(mh=kDmJsnjRCp84_VhO)11.jpg",
    "https://ei.phncdn.com/videos/201004/21/1054308/original/(m=eaf8GgaaaWavb)(mh=kDmJsnjRCp84_VhO)12.jpg",
    "https://ei.phncdn.com/videos/201004/21/1054308/original/(m=eaf8GgaaaWavb)(mh=kDmJsnjRCp84_VhO)13.jpg",
    "https://ei.phncdn.com/videos/201004/21/1054308/original/(m=eaf8GgaaaWavb)(mh=kDmJsnjRCp84_VhO)14.jpg",
    "https://ei.phncdn.com/videos/201004/21/1054308/original/(m=eaf8GgaaaWavb)(mh=kDmJsnjRCp84_VhO)15.jpg",
    "https://ei.phncdn.com/videos/201004/21/1054308/original/(m=eaf8GgaaaWavb)(mh=kDmJsnjRCp84_VhO)16.jpg"
  ],
  "title": "Sexy coed Heather Hurley earns an A in fucking!",
  "tags": [
    "sclip",
    "hushpass.com",
    "interracial",
    "huge-cock",
    "monster-cock",
    "blowjob",
    "cumshot",
    "facial",
    "big-dick",
    "teen",
    "natural-tits",
    "blonde"
  ],
  "categories": [
    "Big Dick",
    "Interracial",
    "Pornstar",
    "18-25"
  ],
  "performers": [
    "heather hurley",
    "Richard Mann"
  ],
  "duration": 665,
  "views": 324230,
  "likes": 561,
  "dislikes": 96
}