{
  "embed": "<iframe src=\"https://www.pornhub.com/embed/e49591a3797ff5d196f2\" frameborder=\"0\" height=\"481\" width=\"608\" scrolling=\"no\"></iframe>",
  "thumbnail": "https://ei.phncdn.com/videos/201010/28/83320/original/(m=eaf8GgaaaWavb)(mh=Hess5XsxV7ak1dy0)3.jpg",
  "screenshots": [
    "https://ei.phncdn.com/videos/201010/28/83320/original/(m=eaf8GgaaaWavb)(mh=Hess5XsxV7ak1dy0)1.jpg",
    "https://ei.phncdn.com/videos/201010/28/83320/original/(m=eaf8GgaaaWavb)(mh=Hess5XsxV7ak1dy0)2.jpg",
    "https://ei.phncdn.com/videos/201010/28/83320/original/(m=eaf8GgaaaWavb)(mh=Hess5XsxV7ak1dy0)3.jpg",
    "https://ei.phncdn.com/videos/201010/28/83320/original/(m=eaf8GgaaaWavb)(mh=Hess5XsxV7ak1dy0)4.jpg",
    "https://ei.phncdn.com/videos/201010/28/83320/original/(m=eaf8GgaaaWavb)(mh=Hess5XsxV7ak1dy0)5.jpg",
    "https://ei.phncdn.com/videos/201010/28/83320/original/(m=eaf8GgaaaWavb)(mh=Hess5XsxV7ak1dy0)6.jpg",
    "https://ei.phncdn.com/videos/201010/28/83320/original/(m=eaf8GgaaaWavb)(mh=Hess5XsxV7ak1dy0)7.jpg",
    "https://ei.phncdn.com/videos/201010/28/83320/original/(m=eaf8GgaaaWavb)(mh=Hess5XsxV7ak1dy0)8.jpg",
    "https://ei.phncdn.com/videos/201010/28/83320/original/(m=eaf8GgaaaWavb)(mh=Hess5XsxV7ak1dy0)9.jpg",
    "https://ei.phncdn.com/videos/201010/28/83320/original/(m=eaf8GgaaaWavb)(mh=Hess5XsxV7ak1dy0)10.jpg",
    "https://ei.phncdn.com/videos/201010/28/83320/original/(m=eaf8GgaaaWavb)(mh=Hess5XsxV7ak1dy0)11.jpg",
    "https://ei.phncdn.com/videos/201010/28/83320/original/(m=eaf8GgaaaWavb)(mh=Hess5XsxV7ak1dy0)12.jpg",
    "https://ei.phncdn.com/videos/201010/28/83320/original/(m=eaf8GgaaaWavb)(mh=Hess5XsxV7ak1dy0)13.jpg",
    "https://ei.phncdn.com/videos/201010/28/83320/original/(m=eaf8GgaaaWavb)(mh=Hess5XsxV7ak1dy0)14.jpg",
    "https://ei.phncdn.com/videos/201010/28/83320/original/(m=eaf8GgaaaWavb)(mh=Hess5XsxV7ak1dy0)15.jpg",
    "https://ei.phncdn.com/videos/201010/28/83320/original/(m=eaf8GgaaaWavb)(mh=Hess5XsxV7ak1dy0)16.jpg"
  ],
  "title": "All about oral",
  "tags": [
    "blonde",
    "blowjob",
    "masturbation",
    "handjob",
    "cum",
    "cumshot",
    "facial",
    "pussy",
    "rubbing",
    "big-tits",
    "skinny"
  ],
  "categories": [
    "Blonde",
    "Blowjob",
    "Pornstar"
  ],
  "performers": [
    "jazy berlin"
  ],
  "duration": 764,
  "views": 135464,
  "likes": 130,
  "dislikes": 43
}