{
  "embed": "<iframe src=\"https://www.pornhub.com/embed/2602e60f3ee5c0cf11f0\" frameborder=\"0\" height=\"481\" width=\"608\" scrolling=\"no\"></iframe>",
  "thumbnail": "https://ei.phncdn.com/videos/201010/28/86937/original/(m=eaf8GgaaaWavb)(mh=DZ2dyefizKfIZGSS)9.jpg",
  "screenshots": [
    "https://ei.phncdn.com/videos/201010/28/86937/original/(m=eaf8GgaaaWavb)(mh=DZ2dyefizKfIZGSS)1.jpg",
    "https://ei.phncdn.com/videos/201010/28/86937/original/(m=eaf8GgaaaWavb)(mh=DZ2dyefizKfIZGSS)2.jpg",
    "https://ei.phncdn.com/videos/201010/28/86937/original/(m=eaf8GgaaaWavb)(mh=DZ2dyefizKfIZGSS)3.jpg",
    "https://ei.phncdn.com/videos/201010/28/86937/original/(m=eaf8GgaaaWavb)(mh=DZ2dyefizKfIZGSS)4.jpg",
    "https://ei.phncdn.com/videos/201010/28/86937/original/(m=eaf8GgaaaWavb)(mh=DZ2dyefizKfIZGSS)5.jpg",
    "https://ei.phncdn.com/videos/201010/28/86937/original/(m=eaf8GgaaaWavb)(mh=DZ2dyefizKfIZGSS)6.jpg",
    "https://ei.phncdn.com/videos/201010/28/86937/original/(m=eaf8GgaaaWavb)(mh=DZ2dyefizKfIZGSS)7.jpg",
    "https://ei.phncdn.com/videos/201010/28/86937/original/(m=eaf8GgaaaWavb)(mh=DZ2dyefizKfIZGSS)8.jpg",
    "https://ei.phncdn.com/videos/201010/28/86937/original/(m=eaf8GgaaaWavb)(mh=DZ2dyefizKfIZGSS)9.jpg",
    "https://ei.phncdn.com/videos/201010/28/86937/original/(m=eaf8GgaaaWavb)(mh=DZ2dyefizKfIZGSS)10.jpg",
    "https://ei.phncdn.com/videos/201010/28/86937/original/(m=eaf8GgaaaWavb)(mh=DZ2dyefizKfIZGSS)11.jpg",
    "https://ei.phncdn.com/videos/201010/28/86937/original/(m=eaf8GgaaaWavb)(mh=DZ2dyefizKfIZGSS)12.jpg",
    "https://ei.phncdn.com/videos/201010/28/86937/original/(m=eaf8GgaaaWavb)(mh=DZ2dyefizKfIZGSS)13.jpg",
    "https://ei.phncdn.com/videos/201010/28/86937/original/(m=eaf8GgaaaWavb)(mh=DZ2dyefizKfIZGSS)14.jpg",
    "https://ei.phncdn.com/videos/201010/28/86937/original/(m=eaf8GgaaaWavb)(mh=DZ2dyefizKfIZGSS)15.jpg",
    "https://ei.phncdn.com/videos/201010/28/86937/original/(m=eaf8GgaaaWavb)(mh=DZ2dyefizKfIZGSS)16.jpg"
  ],
  "title": "Blowjob in the kitchen",
  "tags": [
    "reality",
    "striptease",
    "blonde",
    "blowjob",
    "pov",
    "cum",
    "cumshot",
    "facial",
    "natural-tits"
  ],
  "categories": [
    "Amateur",
    "Blowjob",
    "Cumshot",
    "Pornstar"
  ],
  "performers": [
    "Elizabeth Del Mar"
  ],
  "duration": 1295,
  "views": 622451,
  "likes": 812,
  "dislikes": 210
}