{
  "embed": "<iframe src=\"https://www.pornhub.com/embed/898365604\" frameborder=\"0\" height=\"481\" width=\"608\" scrolling=\"no\"></iframe>",
  "thumbnail": "https://ei.phncdn.com/videos/201005/31/1073386/original/(m=eaf8GgaaaWavb)(mh=KPkosQ6qB7_Sdr3s)11.jpg",
  "screenshots": [
    "https://ei.phncdn.com/videos/201005/31/1073386/original/(m=eaf8GgaaaWavb)(mh=KPkosQ6qB7_Sdr3s)1.jpg",
    "https://ei.phncdn.com/videos/201005/31/1073386/original/(m=eaf8GgaaaWavb)(mh=KPkosQ6qB7_Sdr3s)2.jpg",
    "https://ei.phncdn.com/videos/201005/31/1073386/original/(m=eaf8GgaaaWavb)(mh=KPkosQ6qB7_Sdr3s)3.jpg",
    "https://ei.phncdn.com/videos/201005/31/1073386/original/(m=eaf8GgaaaWavb)(mh=KPkosQ6qB7_Sdr3s)4.jpg",
    "https://ei.phncdn.com/videos/201005/31/1073386/original/(m=eaf8GgaaaWavb)(mh=KPkosQ6qB7_Sdr3s)5.jpg",
    "https://ei.phncdn.com/videos/201005/31/1073386/original/(m=eaf8GgaaaWavb)(mh=KPkosQ6qB7_Sdr3s)6.jpg",
    "https://ei.phncdn.com/videos/201005/31/1073386/original/(m=eaf8GgaaaWavb)(mh=KPkosQ6qB7_Sdr3s)7.jpg",
    "https://ei.phncdn.com/videos/201005/31/1073386/original/(m=eaf8GgaaaWavb)(mh=KPkosQ6qB7_Sdr3s)8.jpg",
    "https://ei.phncdn.com/videos/201005/31/1073386/original/(m=eaf8GgaaaWavb)(mh=KPkosQ6qB7_Sdr3s)9.jpg",
    "https://ei.phncdn.com/videos/201005/31/1073386/original/(m=eaf8GgaaaWavb)(mh=KPkosQ6qB7_Sdr3s)10.jpg",
    "https://ei.phncdn.com/videos/201005/31/1073386/original/(m=eaf8GgaaaWavb)(mh=KPkosQ6qB7_Sdr3s)11.jpg",
    "https://ei.phncdn.com/videos/201005/31/1073386/original/(m=eaf8GgaaaWavb)(mh=KPkosQ6qB7_Sdr3s)12.jpg",
    "https://ei.phncdn.com/videos/201005/31/1073386/original/(m=eaf8GgaaaWavb)(mh=KPkosQ6qB7_Sdr3s)13.jpg",
    "https://ei.phncdn.com/videos/201005/31/1073386/original/(m=eaf8GgaaaWavb)(mh=KPkosQ6qB7_Sdr3s)14.jpg",
    "https://ei.phncdn.com/videos/201005/31/1073386/original/(m=eaf8GgaaaWavb)(mh=KPkosQ6qB7_Sdr3s)15.jpg",
    "https://ei.phncdn.com/videos/201005/31/1073386/original/(m=eaf8GgaaaWavb)(mh=KPkosQ6qB7_Sdr3s)16.jpg"
  ],
  "title": "Italian babe loves her dildo",
  "tags": [
    "sclip",
    "wetandpuffy.com",
    "masturbation",
    "dildo",
    "solo",
    "softcore",
    "toys",
    "euro",
    "brunette",
    "teen"
  ],
  "categories": [
    "Masturbation",
    "Toys",
    "18-25"
  ],
  "performers": [
    ""
  ],
  "duration": 206,
  "views": 114252,
  "likes": 172,
  "dislikes": 56
}