{
  "embed": "<iframe src=\"https://www.pornhub.com/embed/d3388a3fa18dd251f194\" frameborder=\"0\" height=\"481\" width=\"608\" scrolling=\"no\"></iframe>",
  "thumbnail": "https://ei.phncdn.com/videos/201011/01/96539/original/(m=eaf8GgaaaWavb)(mh=ey0CqW_dtKTMN7Ri)12.jpg",
  "screenshots": [
    "https://ei.phncdn.com/videos/201011/01/96539/original/(m=eaf8GgaaaWavb)(mh=ey0CqW_dtKTMN7Ri)1.jpg",
    "https://ei.phncdn.com/videos/201011/01/96539/original/(m=eaf8GgaaaWavb)(mh=ey0CqW_dtKTMN7Ri)2.jpg",
    "https://ei.phncdn.com/videos/201011/01/96539/original/(m=eaf8GgaaaWavb)(mh=ey0CqW_dtKTMN7Ri)3.jpg",
    "https://ei.phncdn.com/videos/201011/01/96539/original/(m=eaf8GgaaaWavb)(mh=ey0CqW_dtKTMN7Ri)4.jpg",
    "https://ei.phncdn.com/videos/201011/01/96539/original/(m=eaf8GgaaaWavb)(mh=ey0CqW_dtKTMN7Ri)5.jpg",
    "https://ei.phncdn.com/videos/201011/01/96539/original/(m=eaf8GgaaaWavb)(mh=ey0CqW_dtKTMN7Ri)6.jpg",
    "https://ei.phncdn.com/videos/201011/01/96539/original/(m=eaf8GgaaaWavb)(mh=ey0CqW_dtKTMN7Ri)7.jpg",
    "https://ei.phncdn.com/videos/201011/01/96539/original/(m=eaf8GgaaaWavb)(mh=ey0CqW_dtKTMN7Ri)8.jpg",
    "https://ei.phncdn.com/videos/201011/01/96539/original/(m=eaf8GgaaaWavb)(mh=ey0CqW_dtKTMN7Ri)9.jpg",
    "https://ei.phncdn.com/videos/201011/01/96539/original/(m=eaf8GgaaaWavb)(mh=ey0CqW_dtKTMN7Ri)10.jpg",
    "https://ei.phncdn.com/videos/201011/01/96539/original/(m=eaf8GgaaaWavb)(mh=ey0CqW_dtKTMN7Ri)11.jpg",
    "https://ei.phncdn.com/videos/201011/01/96539/original/(m=eaf8GgaaaWavb)(mh=ey0CqW_dtKTMN7Ri)12.jpg",
    "https://ei.phncdn.com/videos/201011/01/96539/original/(m=eaf8GgaaaWavb)(mh=ey0CqW_dtKTMN7Ri)13.jpg",
    "https://ei.phncdn.com/videos/201011/01/96539/original/(m=eaf8GgaaaWavb)(mh=ey0CqW_dtKTMN7Ri)14.jpg",
    "https://ei.phncdn.com/videos/201011/01/96539/original/(m=eaf8GgaaaWavb)(mh=ey0CqW_dtKTMN7Ri)15.jpg",
    "https://ei.phncdn.com/videos/201011/01/96539/original/(m=eaf8GgaaaWavb)(mh=ey0CqW_dtKTMN7Ri)16.jpg"
  ],
  "title": "Randi Wright - Expose Rose - Scene 2",
  "tags": [
    "pussylicking",
    "reality",
    "blowjob",
    "hardcore",
    "tight",
    "natural-tits"
  ],
  "categories": [
    "Hardcore",
    "Pornstar",
    "Reality"
  ],
  "performers": [
    "Randi Wright",
    "Rose",
    "Van Damage"
  ],
  "duration": 1121,
  "views": 805557,
  "likes": 815,
  "dislikes": 150
}