{
  "embed": "<iframe src=\"https://www.pornhub.com/embed/95024e6c982c85d43d15\" frameborder=\"0\" height=\"481\" width=\"608\" scrolling=\"no\"></iframe>",
  "thumbnail": "https://ei.phncdn.com/videos/201010/28/84250/original/(m=eaf8GgaaaWavb)(mh=wMc2AIQEtNEM4nrs)16.jpg",
  "screenshots": [
    "https://ei.phncdn.com/videos/201010/28/84250/original/(m=eaf8GgaaaWavb)(mh=wMc2AIQEtNEM4nrs)1.jpg",
    "https://ei.phncdn.com/videos/201010/28/84250/original/(m=eaf8GgaaaWavb)(mh=wMc2AIQEtNEM4nrs)2.jpg",
    "https://ei.phncdn.com/videos/201010/28/84250/original/(m=eaf8GgaaaWavb)(mh=wMc2AIQEtNEM4nrs)3.jpg",
    "https://ei.phncdn.com/videos/201010/28/84250/original/(m=eaf8GgaaaWavb)(mh=wMc2AIQEtNEM4nrs)4.jpg",
    "https://ei.phncdn.com/videos/201010/28/84250/original/(m=eaf8GgaaaWavb)(mh=wMc2AIQEtNEM4nrs)5.jpg",
    "https://ei.phncdn.com/videos/201010/28/84250/original/(m=eaf8GgaaaWavb)(mh=wMc2AIQEtNEM4nrs)6.jpg",
    "https://ei.phncdn.com/videos/201010/28/84250/original/(m=eaf8GgaaaWavb)(mh=wMc2AIQEtNEM4nrs)7.jpg",
    "https://ei.phncdn.com/videos/201010/28/84250/original/(m=eaf8GgaaaWavb)(mh=wMc2AIQEtNEM4nrs)8.jpg",
    "https://ei.phncdn.com/videos/201010/28/84250/original/(m=eaf8GgaaaWavb)(mh=wMc2AIQEtNEM4nrs)9.jpg",
    "https://ei.phncdn.com/videos/201010/28/84250/original/(m=eaf8GgaaaWavb)(mh=wMc2AIQEtNEM4nrs)10.jpg",
    "https://ei.phncdn.com/videos/201010/28/84250/original/(m=eaf8GgaaaWavb)(mh=wMc2AIQEtNEM4nrs)11.jpg",
    "https://ei.phncdn.com/videos/201010/28/84250/original/(m=eaf8GgaaaWavb)(mh=wMc2AIQEtNEM4nrs)12.jpg",
    "https://ei.phncdn.com/videos/201010/28/84250/original/(m=eaf8GgaaaWavb)(mh=wMc2AIQEtNEM4nrs)13.jpg",
    "https://ei.phncdn.com/videos/201010/28/84250/original/(m=eaf8GgaaaWavb)(mh=wMc2AIQEtNEM4nrs)14.jpg",
    "https://ei.phncdn.com/videos/201010/28/84250/original/(m=eaf8GgaaaWavb)(mh=wMc2AIQEtNEM4nrs)15.jpg",
    "https://ei.phncdn.com/videos/201010/28/84250/original/(m=eaf8GgaaaWavb)(mh=wMc2AIQEtNEM4nrs)16.jpg"
  ],
  "title": "Beautiful brunette blows and gets a facial",
  "tags": [
    "asian",
    "brunette",
    "handjob",
    "blowjob",
    "pov",
    "cum",
    "cumshot",
    "facial",
    "pussy",
    "mexican",
    "latina"
  ],
  "categories": [
    "Asian",
    "Blowjob",
    "Cumshot",
    "Pornstar",
    "POV"
  ],
  "performers": [
    "Honney Bunny"
  ],
  "duration": 1584,
  "views": 355721,
  "likes": 528,
  "dislikes": 102
}