{
  "embed": "<iframe src=\"https://www.pornhub.com/embed/b9ba7fd45d7fa420b705\" frameborder=\"0\" height=\"481\" width=\"608\" scrolling=\"no\"></iframe>",
  "thumbnail": "https://ei.phncdn.com/videos/201010/28/84207/original/(m=eaf8GgaaaWavb)(mh=k2FnDkiRi84VgNVG)4.jpg",
  "screenshots": [
    "https://ei.phncdn.com/videos/201010/28/84207/original/(m=eaf8GgaaaWavb)(mh=k2FnDkiRi84VgNVG)1.jpg",
    "https://ei.phncdn.com/videos/201010/28/84207/original/(m=eaf8GgaaaWavb)(mh=k2FnDkiRi84VgNVG)2.jpg",
    "https://ei.phncdn.com/videos/201010/28/84207/original/(m=eaf8GgaaaWavb)(mh=k2FnDkiRi84VgNVG)3.jpg",
    "https://ei.phncdn.com/videos/201010/28/84207/original/(m=eaf8GgaaaWavb)(mh=k2FnDkiRi84VgNVG)4.jpg",
    "https://ei.phncdn.com/videos/201010/28/84207/original/(m=eaf8GgaaaWavb)(mh=k2FnDkiRi84VgNVG)5.jpg",
    "https://ei.phncdn.com/videos/201010/28/84207/original/(m=eaf8GgaaaWavb)(mh=k2FnDkiRi84VgNVG)6.jpg",
    "https://ei.phncdn.com/videos/201010/28/84207/original/(m=eaf8GgaaaWavb)(mh=k2FnDkiRi84VgNVG)7.jpg",
    "https://ei.phncdn.com/videos/201010/28/84207/original/(m=eaf8GgaaaWavb)(mh=k2FnDkiRi84VgNVG)8.jpg",
    "https://ei.phncdn.com/videos/201010/28/84207/original/(m=eaf8GgaaaWavb)(mh=k2FnDkiRi84VgNVG)9.jpg",
    "https://ei.phncdn.com/videos/201010/28/84207/original/(m=eaf8GgaaaWavb)(mh=k2FnDkiRi84VgNVG)10.jpg",
    "https://ei.phncdn.com/videos/201010/28/84207/original/(m=eaf8GgaaaWavb)(mh=k2FnDkiRi84VgNVG)11.jpg",
    "https://ei.phncdn.com/videos/201010/28/84207/original/(m=eaf8GgaaaWavb)(mh=k2FnDkiRi84VgNVG)12.jpg",
    "https://ei.phncdn.com/videos/201010/28/84207/original/(m=eaf8GgaaaWavb)(mh=k2FnDkiRi84VgNVG)13.jpg",
    "https://ei.phncdn.com/videos/201010/28/84207/original/(m=eaf8GgaaaWavb)(mh=k2FnDkiRi84VgNVG)14.jpg",
    "https://ei.phncdn.com/videos/201010/28/84207/original/(m=eaf8GgaaaWavb)(mh=k2FnDkiRi84VgNVG)15.jpg",
    "https://ei.phncdn.com/videos/201010/28/84207/original/(m=eaf8GgaaaWavb)(mh=k2FnDkiRi84VgNVG)16.jpg"
  ],
  "title": "Mmm ...2 on a cock",
  "tags": [
    "lesbian",
    "couch",
    "masturbation",
    "rubbing",
    "latina",
    "brunette",
    "blowjob",
    "pov",
    "natural",
    "big-tits",
    "threesome",
    "group",
    "cum",
    "cumshot",
    "facial"
  ],
  "categories": [
    "Orgy",
    "Blowjob",
    "POV",
    "Threesome"
  ],
  "performers": [
    ""
  ],
  "duration": 1213,
  "views": 242588,
  "likes": 322,
  "dislikes": 57
}