{
  "embed": "<iframe src=\"https://www.pornhub.com/embed/1639729462\" frameborder=\"0\" height=\"481\" width=\"608\" scrolling=\"no\"></iframe>",
  "thumbnail": "https://ei.phncdn.com/videos/201004/21/1054544/original/(m=eaf8GgaaaWavb)(mh=0KsE7tnVCE0reJw2)12.jpg",
  "screenshots": [
    "https://ei.phncdn.com/videos/201004/21/1054544/original/(m=eaf8GgaaaWavb)(mh=0KsE7tnVCE0reJw2)1.jpg",
    "https://ei.phncdn.com/videos/201004/21/1054544/original/(m=eaf8GgaaaWavb)(mh=0KsE7tnVCE0reJw2)2.jpg",
    "https://ei.phncdn.com/videos/201004/21/1054544/original/(m=eaf8GgaaaWavb)(mh=0KsE7tnVCE0reJw2)3.jpg",
    "https://ei.phncdn.com/videos/201004/21/1054544/original/(m=eaf8GgaaaWavb)(mh=0KsE7tnVCE0reJw2)4.jpg",
    "https://ei.phncdn.com/videos/201004/21/1054544/original/(m=eaf8GgaaaWavb)(mh=0KsE7tnVCE0reJw2)5.jpg",
    "https://ei.phncdn.com/videos/201004/21/1054544/original/(m=eaf8GgaaaWavb)(mh=0KsE7tnVCE0reJw2)6.jpg",
    "https://ei.phncdn.com/videos/201004/21/1054544/original/(m=eaf8GgaaaWavb)(mh=0KsE7tnVCE0reJw2)7.jpg",
    "https://ei.phncdn.com/videos/201004/21/1054544/original/(m=eaf8GgaaaWavb)(mh=0KsE7tnVCE0reJw2)8.jpg",
    "https://ei.phncdn.com/videos/201004/21/1054544/original/(m=eaf8GgaaaWavb)(mh=0KsE7tnVCE0reJw2)9.jpg",
    "https://ei.phncdn.com/videos/201004/21/1054544/original/(m=eaf8GgaaaWavb)(mh=0KsE7tnVCE0reJw2)10.jpg",
    "https://ei.phncdn.com/videos/201004/21/1054544/original/(m=eaf8GgaaaWavb)(mh=0KsE7tnVCE0reJw2)11.jpg",
    "https://ei.phncdn.com/videos/201004/21/1054544/original/(m=eaf8GgaaaWavb)(mh=0KsE7tnVCE0reJw2)12.jpg",
    "https://ei.phncdn.com/videos/201004/21/1054544/original/(m=eaf8GgaaaWavb)(mh=0KsE7tnVCE0reJw2)13.jpg",
    "https://ei.phncdn.com/videos/201004/21/1054544/original/(m=eaf8GgaaaWavb)(mh=0KsE7tnVCE0reJw2)14.jpg",
    "https://ei.phncdn.com/videos/201004/21/1054544/original/(m=eaf8GgaaaWavb)(mh=0KsE7tnVCE0reJw2)15.jpg",
    "https://ei.phncdn.com/videos/201004/21/1054544/original/(m=eaf8GgaaaWavb)(mh=0KsE7tnVCE0reJw2)16.jpg"
  ],
  "title": "Jessica Lynn - House of Sluts: Chapter 1 - Brazzers",
  "tags": [
    "bclip",
    "big-dick",
    "big-tits",
    "blonde",
    "blowjob",
    "facial",
    "skinny",
    "big",
    "dick"
  ],
  "categories": [
    "Pornstar"
  ],
  "performers": [
    "Jessica Lynn",
    "Johnny Sins"
  ],
  "duration": 265,
  "views": 469160,
  "likes": 409,
  "dislikes": 79
}