{
  "embed": "<iframe src=\"https://www.pornhub.com/embed/9733a52f555c04f409a7\" frameborder=\"0\" height=\"481\" width=\"608\" scrolling=\"no\"></iframe>",
  "thumbnail": "https://ei.phncdn.com/videos/201011/01/95551/original/(m=eaf8GgaaaWavb)(mh=TNYNIEtRKmpCbG-K)4.jpg",
  "screenshots": [
    "https://ei.phncdn.com/videos/201011/01/95551/original/(m=eaf8GgaaaWavb)(mh=TNYNIEtRKmpCbG-K)1.jpg",
    "https://ei.phncdn.com/videos/201011/01/95551/original/(m=eaf8GgaaaWavb)(mh=TNYNIEtRKmpCbG-K)2.jpg",
    "https://ei.phncdn.com/videos/201011/01/95551/original/(m=eaf8GgaaaWavb)(mh=TNYNIEtRKmpCbG-K)3.jpg",
    "https://ei.phncdn.com/videos/201011/01/95551/original/(m=eaf8GgaaaWavb)(mh=TNYNIEtRKmpCbG-K)4.jpg",
    "https://ei.phncdn.com/videos/201011/01/95551/original/(m=eaf8GgaaaWavb)(mh=TNYNIEtRKmpCbG-K)5.jpg",
    "https://ei.phncdn.com/videos/201011/01/95551/original/(m=eaf8GgaaaWavb)(mh=TNYNIEtRKmpCbG-K)6.jpg",
    "https://ei.phncdn.com/videos/201011/01/95551/original/(m=eaf8GgaaaWavb)(mh=TNYNIEtRKmpCbG-K)7.jpg",
    "https://ei.phncdn.com/videos/201011/01/95551/original/(m=eaf8GgaaaWavb)(mh=TNYNIEtRKmpCbG-K)8.jpg",
    "https://ei.phncdn.com/videos/201011/01/95551/original/(m=eaf8GgaaaWavb)(mh=TNYNIEtRKmpCbG-K)9.jpg",
    "https://ei.phncdn.com/videos/201011/01/95551/original/(m=eaf8GgaaaWavb)(mh=TNYNIEtRKmpCbG-K)10.jpg",
    "https://ei.phncdn.com/videos/201011/01/95551/original/(m=eaf8GgaaaWavb)(mh=TNYNIEtRKmpCbG-K)11.jpg",
    "https://ei.phncdn.com/videos/201011/01/95551/original/(m=eaf8GgaaaWavb)(mh=TNYNIEtRKmpCbG-K)12.jpg",
    "https://ei.phncdn.com/videos/201011/01/95551/original/(m=eaf8GgaaaWavb)(mh=TNYNIEtRKmpCbG-K)13.jpg",
    "https://ei.phncdn.com/videos/201011/01/95551/original/(m=eaf8GgaaaWavb)(mh=TNYNIEtRKmpCbG-K)14.jpg",
    "https://ei.phncdn.com/videos/201011/01/95551/original/(m=eaf8GgaaaWavb)(mh=TNYNIEtRKmpCbG-K)15.jpg",
    "https://ei.phncdn.com/videos/201011/01/95551/original/(m=eaf8GgaaaWavb)(mh=TNYNIEtRKmpCbG-K)16.jpg"
  ],
  "title": "Olivia Olovely - Looks Like Cherries, Tastes Like Cherries - Scene 4",
  "tags": [
    "blowjob",
    "facial",
    "pussy",
    "ass",
    "rubbing",
    "fingering",
    "doggystyle",
    "riding",
    "cum",
    "cumshot",
    "big-ass",
    "big-tits",
    "milf",
    "big-dick",
    "curvy"
  ],
  "categories": [
    "Big Dick",
    "Big Tits",
    "Brunette",
    "MILF",
    "Pornstar"
  ],
  "performers": [
    "Cheyne Collins",
    "Olivia O Lovely"
  ],
  "duration": 1064,
  "views": 1788731,
  "likes": 1635,
  "dislikes": 314
}