{
  "embed": "<iframe src=\"https://www.pornhub.com/embed/4ec13069fe091df5e9a5\" frameborder=\"0\" height=\"481\" width=\"608\" scrolling=\"no\"></iframe>",
  "thumbnail": "https://ei.phncdn.com/videos/201010/28/88071/original/(m=eaf8GgaaaWavb)(mh=qjs7DX-Zr6mjqrLl)16.jpg",
  "screenshots": [
    "https://ei.phncdn.com/videos/201010/28/88071/original/(m=eaf8GgaaaWavb)(mh=qjs7DX-Zr6mjqrLl)1.jpg",
    "https://ei.phncdn.com/videos/201010/28/88071/original/(m=eaf8GgaaaWavb)(mh=qjs7DX-Zr6mjqrLl)2.jpg",
    "https://ei.phncdn.com/videos/201010/28/88071/original/(m=eaf8GgaaaWavb)(mh=qjs7DX-Zr6mjqrLl)3.jpg",
    "https://ei.phncdn.com/videos/201010/28/88071/original/(m=eaf8GgaaaWavb)(mh=qjs7DX-Zr6mjqrLl)4.jpg",
    "https://ei.phncdn.com/videos/201010/28/88071/original/(m=eaf8GgaaaWavb)(mh=qjs7DX-Zr6mjqrLl)5.jpg",
    "https://ei.phncdn.com/videos/201010/28/88071/original/(m=eaf8GgaaaWavb)(mh=qjs7DX-Zr6mjqrLl)6.jpg",
    "https://ei.phncdn.com/videos/201010/28/88071/original/(m=eaf8GgaaaWavb)(mh=qjs7DX-Zr6mjqrLl)7.jpg",
    "https://ei.phncdn.com/videos/201010/28/88071/original/(m=eaf8GgaaaWavb)(mh=qjs7DX-Zr6mjqrLl)8.jpg",
    "https://ei.phncdn.com/videos/201010/28/88071/original/(m=eaf8GgaaaWavb)(mh=qjs7DX-Zr6mjqrLl)9.jpg",
    "https://ei.phncdn.com/videos/201010/28/88071/original/(m=eaf8GgaaaWavb)(mh=qjs7DX-Zr6mjqrLl)10.jpg",
    "https://ei.phncdn.com/videos/201010/28/88071/original/(m=eaf8GgaaaWavb)(mh=qjs7DX-Zr6mjqrLl)11.jpg",
    "https://ei.phncdn.com/videos/201010/28/88071/original/(m=eaf8GgaaaWavb)(mh=qjs7DX-Zr6mjqrLl)12.jpg",
    "https://ei.phncdn.com/videos/201010/28/88071/original/(m=eaf8GgaaaWavb)(mh=qjs7DX-Zr6mjqrLl)13.jpg",
    "https://ei.phncdn.com/videos/201010/28/88071/original/(m=eaf8GgaaaWavb)(mh=qjs7DX-Zr6mjqrLl)14.jpg",
    "https://ei.phncdn.com/videos/201010/28/88071/original/(m=eaf8GgaaaWavb)(mh=qjs7DX-Zr6mjqrLl)15.jpg",
    "https://ei.phncdn.com/videos/201010/28/88071/original/(m=eaf8GgaaaWavb)(mh=qjs7DX-Zr6mjqrLl)16.jpg"
  ],
  "title": "Hot Malezia fucked and facialised",
  "tags": [
    "pornstar",
    "handjob",
    "blowjob",
    "pov",
    "rubbing",
    "riding",
    "ass",
    "doggystyle",
    "cum",
    "cumshot",
    "facial",
    "canadian"
  ],
  "categories": [
    "Blowjob",
    "Cumshot",
    "Pornstar"
  ],
  "performers": [
    "malezia"
  ],
  "duration": 2305,
  "views": 765841,
  "likes": 1090,
  "dislikes": 192
}