{
  "embed": "<iframe src=\"https://www.pornhub.com/embed/5a64ea7b20b72f57129d\" frameborder=\"0\" height=\"481\" width=\"608\" scrolling=\"no\"></iframe>",
  "thumbnail": "https://ei.phncdn.com/videos/200803/19/90348/original/(m=eaf8GgaaaWavb)(mh=zafPKETYyoB8nwnc)4.jpg",
  "screenshots": [
    "https://ei.phncdn.com/videos/200803/19/90348/original/(m=eaf8GgaaaWavb)(mh=zafPKETYyoB8nwnc)1.jpg",
    "https://ei.phncdn.com/videos/200803/19/90348/original/(m=eaf8GgaaaWavb)(mh=zafPKETYyoB8nwnc)2.jpg",
    "https://ei.phncdn.com/videos/200803/19/90348/original/(m=eaf8GgaaaWavb)(mh=zafPKETYyoB8nwnc)3.jpg",
    "https://ei.phncdn.com/videos/200803/19/90348/original/(m=eaf8GgaaaWavb)(mh=zafPKETYyoB8nwnc)4.jpg",
    "https://ei.phncdn.com/videos/200803/19/90348/original/(m=eaf8GgaaaWavb)(mh=zafPKETYyoB8nwnc)5.jpg",
    "https://ei.phncdn.com/videos/200803/19/90348/original/(m=eaf8GgaaaWavb)(mh=zafPKETYyoB8nwnc)6.jpg",
    "https://ei.phncdn.com/videos/200803/19/90348/original/(m=eaf8GgaaaWavb)(mh=zafPKETYyoB8nwnc)7.jpg",
    "https://ei.phncdn.com/videos/200803/19/90348/original/(m=eaf8GgaaaWavb)(mh=zafPKETYyoB8nwnc)8.jpg",
    "https://ei.phncdn.com/videos/200803/19/90348/original/(m=eaf8GgaaaWavb)(mh=zafPKETYyoB8nwnc)9.jpg",
    "https://ei.phncdn.com/videos/200803/19/90348/original/(m=eaf8GgaaaWavb)(mh=zafPKETYyoB8nwnc)10.jpg",
    "https://ei.phncdn.com/videos/200803/19/90348/original/(m=eaf8GgaaaWavb)(mh=zafPKETYyoB8nwnc)11.jpg",
    "https://ei.phncdn.com/videos/200803/19/90348/original/(m=eaf8GgaaaWavb)(mh=zafPKETYyoB8nwnc)12.jpg",
    "https://ei.phncdn.com/videos/200803/19/90348/original/(m=eaf8GgaaaWavb)(mh=zafPKETYyoB8nwnc)13.jpg",
    "https://ei.phncdn.com/videos/200803/19/90348/original/(m=eaf8GgaaaWavb)(mh=zafPKETYyoB8nwnc)14.jpg",
    "https://ei.phncdn.com/videos/200803/19/90348/original/(m=eaf8GgaaaWavb)(mh=zafPKETYyoB8nwnc)15.jpg",
    "https://ei.phncdn.com/videos/200803/19/90348/original/(m=eaf8GgaaaWavb)(mh=zafPKETYyoB8nwnc)16.jpg"
  ],
  "title": "Hot tight college chick sucking, fucking and sucking again",
  "tags": [
    "fullvideo",
    "hot",
    "tight",
    "brunette",
    "hardcore",
    "glasses",
    "facial",
    "cumshot",
    "canadian",
    "blonde",
    "small",
    "tits"
  ],
  "categories": [
    "Brunette",
    "Hardcore",
    "Pornstar",
    "18-25"
  ],
  "performers": [
    "Judy Star"
  ],
  "duration": 3094,
  "views": 750351,
  "likes": 896,
  "dislikes": 794
}